{"version":"1.0.5","buildNumber":6,"notes":"Real feel: haptics now follow each video's sound — music, wind and ambience become light-to-heavy vibration, analysed during processing. Creators: VR/MR uploads are checked for real 360 compatibility, and you can enroll new places right from the studio. Tap any photo to view fullscreen with save. Cleaner settings. Places now come live from the platform, not built in.","apkUrl":"https://pub-bd504c26d89a4a0494ff94ee6cc0f999.r2.dev/apk/mrtouride.apk","apkAvailable":true}
